docstring2tsx/__init__.py
docstring2tsx/__main__.py
docstring2tsx/cli.py
docstring2tsx/converter.py
docstring2tsx-0.0.7.dist-info/licenses/LICENSE
utils/__init__.py
utils/shared.py
utils/signature_formatter.py
docstring2tsx-0.0.7.dist-info/METADATA
docstring2tsx-0.0.7.dist-info/WHEEL
docstring2tsx-0.0.7.dist-info/entry_points.txt
docstring2tsx-0.0.7.dist-info/top_level.txt
docstring2tsx-0.0.7.dist-info/RECORD
