Metadata-Version: 2.4
Name: docstring2tsx
Version: 0.0.7
Summary: A tool to convert Google-style docstrings to TSX format for Next.js documentation
Author-email: Vladimir Iglovikov <iglovikov@gmail.com>
Maintainer: Vladimir Iglovikov
License: # CUSTOM LICENSE AGREEMENT FOR GOOGLE DOCSTRING TO MARKDOWN CONVERTER
Project-URL: bug tracker, https://github.com/ternaus/google-docstring-2tsx/issues
Project-URL: homepage, https://github.com/ternaus/google-docstring-2tsx
Keywords: docstring,documentation,google-style,nextjs,parser,python,react,tsx
Classifier: Development Status :: 5 - Production/Stable
Classifier: Intended Audience :: Developers
Classifier: Intended Audience :: Science/Research
Classifier: Operating System :: OS Independent
Classifier: Programming Language :: Python
Classifier: Programming Language :: Python :: 3 :: Only
Classifier: Programming Language :: Python :: 3.12
Classifier: Programming Language :: Python :: 3.13
Classifier: Topic :: Scientific/Engineering :: Artificial Intelligence
Classifier: Topic :: Software Development :: Documentation
Classifier: Topic :: Software Development :: Libraries
Classifier: Topic :: Software Development :: Libraries :: Python Modules
Classifier: Typing :: Typed
Requires-Python: >=3.12
License-File: LICENSE
Requires-Dist: google-docstring-parser>=0.0.7
Requires-Dist: tqdm>=4.65
Provides-Extra: dev
Requires-Dist: pre-commit>=3.5; extra == "dev"
Requires-Dist: pytest>=8.3.3; extra == "dev"
Dynamic: license-file
